hi_mingk42/__init__.py
hi_mingk42/hello.py
hi_Mingk42-0.7.0.dist-info/METADATA
hi_Mingk42-0.7.0.dist-info/WHEEL
hi_Mingk42-0.7.0.dist-info/entry_points.txt
hi_Mingk42-0.7.0.dist-info/top_level.txt
hi_Mingk42-0.7.0.dist-info/RECORD
