Metadata-Version: 2.1
Name: hi_Mingk42
Version: 0.7.0
Summary: Default template for PDM package
Author-email: Mingk42 <xoals123456t@gmail.com>
License: MIT
Requires-Python: ==3.12.*
